pyargos/__init__.py
pyargos/button.py
pyargos/core.py
pyargos/dropdown.py
pyargos/line.py
pyargos/utils.py
pyargos-0.1.1.dist-info/LICENSE
pyargos-0.1.1.dist-info/METADATA
pyargos-0.1.1.dist-info/WHEEL
pyargos-0.1.1.dist-info/top_level.txt
pyargos-0.1.1.dist-info/RECORD
