Metadata-Version: 2.1
Name: pyargos
Version: 0.1.1
Summary: A Python library for easier interfacing with Argos
Home-page: https://github.com/naanselmo/pyargos
Author: Nuno Anselmo
Author-email: pyargos@nunoanselmo.me
License: GPLv3
Project-URL: Bug Tracker, https://github.com/naanselmo/pyargos/issues
Platform: UNKNOWN
Classifier: Programming Language :: Python :: 3
Classifier: Programming Language :: Python :: 3.9
Classifier: Intended Audience :: Developers
Classifier: Natural Language :: English
Classifier: Environment :: X11 Applications :: Gnome
Classifier: Operating System :: POSIX
Requires-Python: >=3.9
License-File: LICENSE
